{
  "tags": [
    {
      "name": "release",
      "version": "0.5.1",
      "commit": "b6b145b",
      "upstream": "Releases",
      "lastUpdated": "2021-04-21T19:00:35.519Z"
    },
    {
      "name": "testing",
      "version": "",
      "commit": "",
      "upstream": "",
      "lastUpdated": ""
    },
    {
      "name": "nightly",
      "version": "f81b334d617cf5ebbc9969dad4d2b6c50d2015b8",
      "commit": "2542a21",
      "upstream": "Every commit to python3-dev",
      "lastUpdated": "2021-04-23T18:02:46.665Z"
    }
  ],
  "pulls": 4118555,
  "stars": 7
}
